salmon_lib/__init__.py
salmon_lib/bound_patcher.py
salmon_lib/crisp_map.py
salmon_lib/crisp_to_salmon.py
salmon_lib/salmon.py
salmon_lib/zhp.py
salmon_lib/zhp_markdown.py
salmon_lib/parsers/__init__.py
salmon_lib/parsers/bse.py
salmon_lib/parsers/cei.py
salmon_lib/parsers/enh.py
salmon_lib/parsers/evo.py
salmon_lib/parsers/fp.py
salmon_lib/parsers/idl.py
salmon_lib/parsers/mat.py
salmon_lib/parsers/opt.py
salmon_lib/parsers/pnv.py
salmon_lib/parsers/printer.py
salmon_lib/resources/__init__.py
salmon_lib/resources/crisp_map_data.json
salmon_lib-0.3.4.dist-info/LICENSE
salmon_lib-0.3.4.dist-info/METADATA
salmon_lib-0.3.4.dist-info/WHEEL
salmon_lib-0.3.4.dist-info/top_level.txt
salmon_lib-0.3.4.dist-info/RECORD
